README.md
setup.cfg
setup.py
doc/_build/man/privacyidea.1
privacyideaadm.egg-info/PKG-INFO
privacyideaadm.egg-info/SOURCES.txt
privacyideaadm.egg-info/dependency_links.txt
privacyideaadm.egg-info/requires.txt
privacyideaadm.egg-info/top_level.txt
privacyideautils/__init__.py
privacyideautils/clientutils.py
privacyideautils/etokenng.py
privacyideautils/initdaplug.py
privacyideautils/nitrokey.py
privacyideautils/offline.py
privacyideautils/pytoken-totp.py
privacyideautils/pytoken.template.py
privacyideautils/yubikey.py
privacyideautils/commands/__init__.py
privacyideautils/commands/audit.py
privacyideautils/commands/certificate.py
privacyideautils/commands/config.py
privacyideautils/commands/machine.py
privacyideautils/commands/realm.py
privacyideautils/commands/resolver.py
privacyideautils/commands/securitymodule.py
privacyideautils/commands/token.py
privacyideautils/commands/user.py
privacyideautils/commands/yubikey.py
scripts/privacyidea
scripts/privacyidea-authorizedkeys
scripts/privacyidea-check-offline-otp
scripts/privacyidea-enroll-yubikey-piv
scripts/privacyidea-get-offline-otp
scripts/privacyidea-luks-assign
scripts/privacyidea-validate