Metadata-Version: 1.0
Name: privacyideaadm
Version: 3.0
Summary: privacyIDEA admin Client
Home-page: http://www.privacyidea.org
Author: Cornelius Kölbel
Author-email: cornelius@privacyidea.org
License: AGPLv3
Platform: UNKNOWN
